langchain_meta/__init__.py
langchain_meta/chat_meta_llama/__init__.py
langchain_meta/chat_meta_llama/chat_async.py
langchain_meta/chat_meta_llama/chat_sync.py
langchain_meta/chat_meta_llama/serialization.py
langchain_meta/chat_models.py
langchain_meta/constants.py
langchain_meta/utils.py
langchain_meta-0.4.2.dist-info/LICENSE
langchain_meta-0.4.2.dist-info/METADATA
langchain_meta-0.4.2.dist-info/WHEEL
langchain_meta-0.4.2.dist-info/RECORD
