Metadata-Version: 2.3
Name: langchain-meta
Version: 0.4.2
Summary: An integration wrapper package connecting Meta's Llama API client and LangGraph. Implements ChatModel interface from LangChain.
License: MIT
Author: Matt Petters
Author-email: mcpetters@gmail.com
Requires-Python: >=3.9,<3.14
Classifier: License :: OSI Approved :: MIT License
Classifier: Programming Language :: Python :: 3
Classifier: Programming Language :: Python :: 3.9
Classifier: Programming Language :: Python :: 3.10
Classifier: Programming Language :: Python :: 3.11
Classifier: Programming Language :: Python :: 3.12
Classifier: Programming Language :: Python :: 3.13
Requires-Dist: langchain (>=0.3.25)
Requires-Dist: langchain-core (>=0.1.33)
Requires-Dist: llama-api-client (>=0.1.0)
Requires-Dist: pydantic (>=1.10,<3.0)
Requires-Dist: pytest (>=7.4.0)
Requires-Dist: pytest-asyncio (>=0.23.0)
Requires-Dist: python-dotenv (>=1.0.0)
Requires-Dist: regex (>=2023.0.0)
Requires-Dist: twine (>=6.0.0)
Requires-Dist: typing-extensions (>=4.8.0)
Project-URL: Repository, https://github.com/mattpetters/langchain-meta
Project-URL: Release Notes, https://github.com/mattpetters/langchain-meta/releases?q=tag%3A%22meta%3D%3D0%22&expanded=true
Project-URL: Source Code, https://github.com/mattpetters/langchain-meta
